[
	{
		"type":"sphere",
		"center":[
			0,
			0,
			0
		],
		"radius":0.5
	},
	{
		"type":"sphere",
		"center":[
			2.624397393383577e-7,
			-1.875835835244292e-7,
			-2.3651169613392997e-7
		],
		"radius":0.5
	},
	{
		"type":"sphere",
		"center":[
			5.248794786767154e-7,
			-3.751671670488584e-7,
			-4.7302339226785993e-7
		],
		"radius":0.5
	},
	{
		"type":"sphere",
		"center":[
			7.873192180150731e-7,
			-5.627507505732876e-7,
			-7.095350884017898e-7
		],
		"radius":0.5
	},
	{
		"type":"zero"
	}
]