[
	{
		"type":"sphere",
		"center":[
			0,
			0,
			0
		],
		"radius":0.5
	},
	{
		"type":"sphere",
		"center":[
			8.07655634904122e-7,
			-3.5818938369736036e-7,
			-4.6839378818908793e-7
		],
		"radius":0.5
	},
	{
		"type":"sphere",
		"center":[
			1.6153112698082443e-6,
			-7.163787673947206e-7,
			-9.367875763781759e-7
		],
		"radius":0.5
	},
	{
		"type":"sphere",
		"center":[
			2.422966904712366e-6,
			-1.074568151092081e-6,
			-1.4051813645672637e-6
		],
		"radius":0.5
	},
	{
		"type":"zero"
	}
]